LICENSE
cleanocr/__init__.py
cleanocr/models/__init__.py
cleanocr/models/net.py
cleanocr/test.py
cleanocr-0.1.4.dist-info/entry_points.txt
cleanocr-0.1.4.dist-info/LICENSE
cleanocr-0.1.4.dist-info/WHEEL
cleanocr-0.1.4.dist-info/METADATA
cleanocr-0.1.4.dist-info/RECORD
